download_car/__init__.py
download_car/exceptions.py
download_car/polygon.py
download_car/sicar.py
download_car/state.py
download_car/url.py
download_car/drivers/__init__.py
download_car/drivers/captcha.py
download_car/drivers/paddle.py
download_car/drivers/tesseract.py
download_car-1.0.0.dist-info/licenses/LICENSE
download_car-1.0.0.dist-info/METADATA
download_car-1.0.0.dist-info/WHEEL
download_car-1.0.0.dist-info/top_level.txt
download_car-1.0.0.dist-info/RECORD
