Metadata-Version: 2.4
Name: download-car
Version: 1.0.0
Summary: download-car - Tool designed for students, researchers, data scientists or anyone who would like to have access to download-car files.
Author-email: Ricardo Malnati <ricardomalnati@gmail.com>
License: # LICENSE
Project-URL: Homepage, https://github.com/Malnati/download-car
Project-URL: Bug Tracker, https://github.com/Malnati/download-car/issues
Requires-Python: <3.13,>=3.10
License-File: LICENSE
Requires-Dist: httpx>=0.28.1
Requires-Dist: urllib3>=2.3.0
Requires-Dist: pytesseract>=0.3.13
Requires-Dist: opencv-python>=4.11.0.86
Requires-Dist: numpy>=2.0.2
Requires-Dist: tqdm>=4.67.1
Requires-Dist: matplotlib>=3.10.0
Requires-Dist: beautifulsoup4>=4.13.4
Requires-Dist: geopandas>=0.14.0
Requires-Dist: fiona>=1.9.0
Requires-Dist: fastapi
Requires-Dist: uvicorn
Requires-Dist: python-multipart
Provides-Extra: paddle
Requires-Dist: paddlepaddle>=3.0.0; extra == "paddle"
Requires-Dist: paddleocr>=2.10.0; extra == "paddle"
Provides-Extra: dev
Requires-Dist: coverage; extra == "dev"
Requires-Dist: interrogate; extra == "dev"
Requires-Dist: black; extra == "dev"
Requires-Dist: coveralls; extra == "dev"
Dynamic: license-file
